pretty/__init__.py
pretty/girl/__init__.py
pretty/girl/message.py
gmy-0.3.dist-info/METADATA
gmy-0.3.dist-info/WHEEL
gmy-0.3.dist-info/top_level.txt
gmy-0.3.dist-info/RECORD
