Metadata-Version: 2.1
Name: gmy
Version: 0.3
Summary: 高梦瑶   谭茜文
Author: gmy
License: UNKNOWN
Platform: UNKNOWN
